examples/__init__.py
sciterra/__init__.py
sciterra/librarians/__init__.py
sciterra/librarians/adslibrarian.py
sciterra/librarians/librarian.py
sciterra/librarians/s2librarian.py
sciterra/mapping/__init__.py
sciterra/mapping/atlas.py
sciterra/mapping/cartography.py
sciterra/mapping/publication.py
sciterra/mapping/topography.py
sciterra/mapping/tracing.py
sciterra/misc/__init__.py
sciterra/misc/analysis.py
sciterra/misc/utils.py
sciterra/vectorization/__init__.py
sciterra/vectorization/bow.py
sciterra/vectorization/gpt2.py
sciterra/vectorization/preprocessing.py
sciterra/vectorization/projection.py
sciterra/vectorization/sbert.py
sciterra/vectorization/scibert.py
sciterra/vectorization/vectorizer.py
sciterra/vectorization/word2vec.py
tests/__init__.py
tests/test_atlas.py
tests/test_cartography.py
tests/test_librarian.py
tests/test_publication.py
tests/test_tracing.py
tests/test_vectorization.py
sciterra-0.0.21.dist-info/METADATA
sciterra-0.0.21.dist-info/WHEEL
sciterra-0.0.21.dist-info/top_level.txt
sciterra-0.0.21.dist-info/RECORD
