Metadata-Version: 2.1
Name: sciterra
Version: 0.0.21
Summary: Scientific literature data exploration analysis
Home-page: https://github.com/nathimel/sciterra
Author: Nathaniel Imel
Author-email: nimel@uci.edu
Project-URL: Bug Tracker, https://github.com/nathimel/sciterra/issues
Classifier: Programming Language :: Python :: 3
Classifier: License :: OSI Approved :: MIT License
Requires-Dist: ads
Requires-Dist: bibtexparser
Requires-Dist: gensim
Requires-Dist: numpy
Requires-Dist: pandas
Requires-Dist: plotnine
Requires-Dist: scikit-learn
Requires-Dist: scipy ==1.10.1
Requires-Dist: sentence-transformers
Requires-Dist: semanticscholar ==0.5.0
Requires-Dist: spacy
Requires-Dist: torch
Requires-Dist: transformers
